examples/nist_lre/__init__.py
examples/nist_sre/__init__.py
examples/nist_sre/analyze.py
examples/nist_sre/analyze_data.py
examples/nist_sre/feature_recipes.py
examples/nist_sre/helpers.py
examples/nist_sre/make_score.py
examples/nist_sre/speech_augmentation.py
examples/nist_sre/speech_features_extraction.py
examples/nist_sre/train_evec.py
examples/nist_sre/train_xvec.py
examples/tidigits/__init__.py
examples/tidigits/ivec.py
examples/tidigits/single_digit_e2e.py
examples/tidigits/speech_features_extraction.py
examples/tidigits/tidigits_preprocessor.py
examples/tidigits/tvec.py
examples/tidigits/utils.py
examples/tidigits/xvec.py
examples/voxceleb/__init__.py
examples/voxceleb/feature_recipes.py
examples/voxceleb/speech_features_extraction.py
examples/voxceleb/train_ivec.py
examples/voxceleb/train_xvec.py
examples/voxceleb/utils.py
odin/__init__.py
odin/maths.py
odin/stats.py
odin/backend/__init__.py
odin/backend/keras_callbacks.py
odin/backend/keras_helpers.py
odin/backend/losses.py
odin/backend/metrics.py
odin/backend/tensor.py
odin/backend/tf_utils.py
odin/bay/__init__.py
odin/bay/distribution_alias.py
odin/bay/helpers.py
odin/bay/distribution_layers/__init__.py
odin/bay/distribution_layers/basic.py
odin/bay/distribution_layers/count_layers.py
odin/bay/distribution_layers/mixture_layers.py
odin/bay/distributions/__init__.py
odin/bay/distributions/logarizmed.py
odin/bay/distributions/negative_binomial_disp.py
odin/bay/distributions/normal_gamma.py
odin/bay/distributions/quantized.py
odin/bay/distributions/utils.py
odin/bay/distributions/zero_inflated.py
odin/bay/mixed_membership/__init__.py
odin/bay/mixed_membership/grade_membership_model.py
odin/bay/mixed_membership/latent_dirichlet_allocation.py
odin/fuel/__init__.py
odin/fuel/databases.py
odin/fuel/dataset.py
odin/fuel/loaders.py
odin/fuel/mmap_array.py
odin/ml/__init__.py
odin/ml/base.py
odin/ml/decompositions.py
odin/ml/fast_tsne.py
odin/ml/gmm_classifier.py
odin/ml/gmm_tmat.py
odin/ml/ivector.py
odin_ai-1.1.1.dist-info/LICENSE
odin_ai-1.1.1.dist-info/METADATA
odin_ai-1.1.1.dist-info/WHEEL
odin_ai-1.1.1.dist-info/top_level.txt
odin_ai-1.1.1.dist-info/RECORD
